{"gems":{"name":"phlex-icons-lucide","downloads":15139,"version":"2.38.0","version_created_at":"2025-09-12T17:43:48.392Z","version_downloads":16,"platform":"ruby","authors":"Ali Hamdi Ali Fadel","info":"Lucide icons library for Phlex","licenses":["MIT"],"metadata":{"homepage_uri":"https://github.com/AliOsm/phlex-icons","changelog_uri":"https://github.com/AliOsm/phlex-icons/blob/main/CHANGELOG.md","source_code_uri":"https://github.com/AliOsm/phlex-icons","allowed_push_host":"https://rubygems.org","rubygems_mfa_required":"true"},"yanked":false,"sha":"382adcc1ec1c488edee8d62789fbd099b275f4c748a496a94873f66b4b46cb62","spec_sha":"70511e8c6bfaa5b71aa71ed15e33f60469f8e4acfb4c8fe6737d5683558f41a8","project_uri":"https://rubygems.org/gems/phlex-icons-lucide","gem_uri":"https://rubygems.org/gems/phlex-icons-lucide-2.38.0.gem","homepage_uri":"https://github.com/AliOsm/phlex-icons","wiki_uri":null,"documentation_uri":null,"mailing_list_uri":null,"source_code_uri":"https://github.com/AliOsm/phlex-icons","bug_tracker_uri":null,"changelog_uri":"https://github.com/AliOsm/phlex-icons/blob/main/CHANGELOG.md","funding_uri":null,"dependencies":{"development":[],"runtime":[{"name":"phlex","requirements":">= 1.11"}]}},"vcs_name":"GitHub","ci":1,"github_actions":1,"vcs_uri":"https://github.com/AliOsm/phlex-icons"}