{"gems":{"name":"liquid","downloads":123127921,"version":"5.12.0","version_created_at":"2026-03-18T15:56:32.853Z","version_downloads":111,"platform":"ruby","authors":"Tobias Lütke","info":"A secure, non-evaling end user template engine with aesthetic markup.","licenses":["MIT"],"metadata":{"allowed_push_host":"https://rubygems.org"},"yanked":false,"sha":"5a3c2c2430cd925d21c53e4ed9abea52cd0a9da53b541422f81dee79aca2a673","spec_sha":"f2c96f608301e4fde868474ca362f706432d415b9834ddba398e430b6bddc1f3","project_uri":"https://rubygems.org/gems/liquid","gem_uri":"https://rubygems.org/gems/liquid-5.12.0.gem","homepage_uri":"https://shopify.github.io/liquid/","wiki_uri":"","documentation_uri":"https://www.rubydoc.info/gems/liquid/5.12.0","mailing_list_uri":"","source_code_uri":"https://github.com/Shopify/liquid","bug_tracker_uri":"","changelog_uri":null,"funding_uri":null,"dependencies":{"development":[{"name":"minitest","requirements":">= 0"},{"name":"rake","requirements":"~> 13.0"}],"runtime":[{"name":"bigdecimal","requirements":">= 0"},{"name":"strscan","requirements":">= 3.1.1"}]}},"vcs_name":"GitHub","ci":1,"github_actions":1,"vcs_uri":"https://github.com/Shopify/liquid"}