{"gems":{"name":"google-cloud-ai_platform-v1","downloads":967860,"version":"1.24.0","version_created_at":"2025-09-29T04:22:06.369Z","version_downloads":26,"platform":"ruby","authors":"Google LLC","info":"Vertex AI enables data scientists, developers, and AI newcomers to create custom machine learning models specific to their business needs by leveraging Google's state-of-the-art transfer learning and innovative AI research. Note that google-cloud-ai_platform-v1 is a version-specific client library. For most uses, we recommend installing the main client library google-cloud-ai_platform instead. See the readme for more details.","licenses":["Apache-2.0"],"metadata":{},"yanked":false,"sha":"edfac20b790c7b90eedb08274dd46597bcd2dbe7ce2eb9b3d6b1d6cc210d6033","spec_sha":"1c0388cd6dccaae69547f9f32a8de804546cd1dd534d08013f4dc79db0af7c3c","project_uri":"https://rubygems.org/gems/google-cloud-ai_platform-v1","gem_uri":"https://rubygems.org/gems/google-cloud-ai_platform-v1-1.24.0.gem","homepage_uri":"https://github.com/googleapis/google-cloud-ruby","wiki_uri":null,"documentation_uri":"https://www.rubydoc.info/gems/google-cloud-ai_platform-v1/1.24.0","mailing_list_uri":null,"source_code_uri":null,"bug_tracker_uri":null,"changelog_uri":null,"funding_uri":null,"dependencies":{"development":[],"runtime":[{"name":"gapic-common","requirements":"~> 1.2"},{"name":"google-cloud-errors","requirements":"~> 1.0"},{"name":"google-cloud-location","requirements":"~> 1.0"},{"name":"google-iam-v1","requirements":"~> 1.3"}]}},"vcs_name":"GitHub","ci":1,"github_actions":1,"vcs_uri":"https://github.com/googleapis/google-cloud-ruby"}