{"gems":{"name":"puppet_metadata","downloads":239292,"version":"6.0.0","version_created_at":"2025-12-28T17:31:30.457Z","version_downloads":35,"platform":"ruby","authors":"Vox Pupuli, Ewoud Kohl van Wijngaarden","info":"A package that provides abstractions for the Puppet Metadata","licenses":["Apache-2.0"],"metadata":{},"yanked":false,"sha":"27f1e9f73b155d606d9a4895f2ec4a020e3c0978b87dca43243a20283679f781","spec_sha":"f1225cba47bcea5d29e2d98ae751d311ea47ae91c7ad13c5fde31b6056dca095","project_uri":"https://rubygems.org/gems/puppet_metadata","gem_uri":"https://rubygems.org/gems/puppet_metadata-6.0.0.gem","homepage_uri":"https://github.com/voxpupuli/puppet_metadata","wiki_uri":null,"documentation_uri":"https://www.rubydoc.info/gems/puppet_metadata/6.0.0","mailing_list_uri":null,"source_code_uri":null,"bug_tracker_uri":null,"changelog_uri":null,"funding_uri":null,"dependencies":{"development":[{"name":"rake","requirements":"~> 13.0"},{"name":"rdoc","requirements":">= 6.0, < 8"},{"name":"rspec","requirements":"~> 3.0"},{"name":"rspec-its","requirements":">= 1.0, < 3"},{"name":"voxpupuli-rubocop","requirements":"~> 5.1.0"},{"name":"yard","requirements":"~> 0.9"}],"runtime":[{"name":"metadata-json-lint","requirements":">= 2.0, < 6"},{"name":"semantic_puppet","requirements":"~> 1.0"}]}},"vcs_name":"GitHub","ci":1,"github_actions":1,"vcs_uri":"https://github.com/voxpupuli/puppet_metadata"}