{"gems":{"name":"pragmater","downloads":99069,"version":"14.3.0","version_created_at":"2024-03-27T01:49:49.072Z","version_downloads":10,"platform":"ruby","authors":"Brooke Kuhlmann","info":"A command line interface for managing pragma comments.","licenses":["Hippocratic-2.1"],"metadata":{"label":"Pragmater","funding_uri":"https://github.com/sponsors/bkuhlmann","changelog_uri":"https://alchemists.io/projects/pragmater/versions","bug_tracker_uri":"https://github.com/bkuhlmann/pragmater/issues","source_code_uri":"https://github.com/bkuhlmann/pragmater","documentation_uri":"https://alchemists.io/projects/pragmater","rubygems_mfa_required":"true"},"yanked":false,"sha":"67fe06bce581ec8783f038d0c7f4ee19901b8e5d594a886870b4b8e108c03123","project_uri":"https://rubygems.org/gems/pragmater","gem_uri":"https://rubygems.org/gems/pragmater-14.3.0.gem","homepage_uri":"https://alchemists.io/projects/pragmater","wiki_uri":null,"documentation_uri":"https://alchemists.io/projects/pragmater","mailing_list_uri":null,"source_code_uri":"https://github.com/bkuhlmann/pragmater","bug_tracker_uri":"https://github.com/bkuhlmann/pragmater/issues","changelog_uri":"https://alchemists.io/projects/pragmater/versions","funding_uri":"https://github.com/sponsors/bkuhlmann","dependencies":{"development":[],"runtime":[{"name":"cogger","requirements":"~> 0.15"},{"name":"dry-container","requirements":"~> 0.11"},{"name":"dry-schema","requirements":"~> 1.13"},{"name":"etcher","requirements":"~> 1.0"},{"name":"infusible","requirements":"~> 3.4"},{"name":"refinements","requirements":"~> 12.1"},{"name":"runcom","requirements":"~> 11.0"},{"name":"sod","requirements":"~> 0.4"},{"name":"spek","requirements":"~> 3.0"},{"name":"zeitwerk","requirements":"~> 2.6"}]}},"vcs_name":"GitHub","ci":1,"circleci":1,"vcs_uri":"https://github.com/bkuhlmann/pragmater"}