{"gems":{"name":"decidim-reporting_proposals","downloads":1831,"version":"0.6.1","version_created_at":"2024-05-09T08:35:45.141Z","version_downloads":11,"platform":"ruby","authors":"Ivan Vergés","info":"A module for Decidim that facilitates the creation of proposals related to geolocated issues in a city","licenses":["AGPL-3.0"],"metadata":{"rubygems_mfa_required":"true"},"yanked":false,"sha":"a68e7de2dc8976f418fa949a2c18735786bc847a1e93f7908ae56228b9afd841","project_uri":"https://rubygems.org/gems/decidim-reporting_proposals","gem_uri":"https://rubygems.org/gems/decidim-reporting_proposals-0.6.1.gem","homepage_uri":"https://github.com/openpoke/decidim-module-reporting_proposals","wiki_uri":null,"documentation_uri":"https://www.rubydoc.info/gems/decidim-reporting_proposals/0.6.1","mailing_list_uri":null,"source_code_uri":null,"bug_tracker_uri":null,"changelog_uri":null,"funding_uri":null,"dependencies":{"development":[{"name":"decidim-accountability","requirements":">= 0.28.1, < 0.29"},{"name":"decidim-budgets","requirements":">= 0.28.1, < 0.29"},{"name":"decidim-dev","requirements":">= 0.28.1, < 0.29"},{"name":"decidim-elections","requirements":">= 0.28.1, < 0.29"},{"name":"decidim-meetings","requirements":">= 0.28.1, < 0.29"},{"name":"decidim-templates","requirements":">= 0.28.1, < 0.29"}],"runtime":[{"name":"decidim-admin","requirements":">= 0.28.1, < 0.29"},{"name":"decidim-core","requirements":">= 0.28.1, < 0.29"},{"name":"decidim-participatory_processes","requirements":">= 0.28.1, < 0.29"},{"name":"decidim-proposals","requirements":">= 0.28.1, < 0.29"},{"name":"deface","requirements":">= 1.9"}]}},"vcs_name":"GitHub","ci":null,"vcs_error":"ERROR","vcs_uri":"https://github.com/openpoke/decidim-module-reporting_proposals"}