{"gems":{"name":"bridgeapi_client","downloads":288,"version":"1.0.3","version_created_at":"2026-03-05T09:34:12.917Z","version_downloads":32,"platform":"ruby","authors":"Olivier Buffon, Thomas Andrieu","info":"Thanks to a safe and automated access to bank data, Bridge powered by Bankin' provides competitive and smart solutions to build conversion-driver financial services.","licenses":["MIT"],"metadata":{"homepage_uri":"https://github.com/neatops/bridgeapi","changelog_uri":"https://github.com/neatops/bridgeapi/blob/main/CHANGELOG.md","source_code_uri":"https://github.com/neatops/bridgeapi","rubygems_mfa_required":"true"},"yanked":false,"sha":"47a0279101f35c496367100c173df863f80243b55d665151c3a401795d75f1b8","spec_sha":"2a59340c70c8cb8d0892edeba436ac76c9783763dca765eba20740fdf75cbe89","project_uri":"https://rubygems.org/gems/bridgeapi_client","gem_uri":"https://rubygems.org/gems/bridgeapi_client-1.0.3.gem","homepage_uri":"https://github.com/neatops/bridgeapi","wiki_uri":null,"documentation_uri":null,"mailing_list_uri":null,"source_code_uri":"https://github.com/neatops/bridgeapi","bug_tracker_uri":null,"changelog_uri":"https://github.com/neatops/bridgeapi/blob/main/CHANGELOG.md","funding_uri":null,"dependencies":{"development":[],"runtime":[]}},"vcs_name":"GitHub","ci":1,"github_actions":1,"vcs_uri":"https://github.com/neatops/bridgeapi"}