{"gems":{"name":"rails-autoscale-web","downloads":749363,"version":"1.10.0","version_created_at":"2025-02-17T19:36:23.396Z","version_downloads":18,"platform":"ruby","authors":"Adam McCrea, Carlos Antonio da Silva, Jon Sullivan","info":"Autoscaling for Ruby on Rails applications.","licenses":["MIT"],"metadata":{"homepage_uri":"https://judoscale.com","changelog_uri":"https://github.com/judoscale/judoscale-ruby/blob/main/CHANGELOG.md","bug_tracker_uri":"https://github.com/judoscale/judoscale-ruby/issues","source_code_uri":"https://github.com/judoscale/judoscale-ruby","documentation_uri":"https://judoscale.com/docs"},"yanked":false,"sha":"9d737fcd0c95ac9b9f2328eabeb9bbd4ea1f1700a306114fb65eee0dc0a9004e","spec_sha":"835c576732a47e09cf773649d60fd9d561b9f2ec01c9ccc81c2e50e97a5dfa3a","project_uri":"https://rubygems.org/gems/rails-autoscale-web","gem_uri":"https://rubygems.org/gems/rails-autoscale-web-1.10.0.gem","homepage_uri":"https://judoscale.com","wiki_uri":null,"documentation_uri":"https://judoscale.com/docs","mailing_list_uri":null,"source_code_uri":"https://github.com/judoscale/judoscale-ruby","bug_tracker_uri":"https://github.com/judoscale/judoscale-ruby/issues","changelog_uri":"https://github.com/judoscale/judoscale-ruby/blob/main/CHANGELOG.md","funding_uri":null,"dependencies":{"development":[],"runtime":[{"name":"judoscale-rails","requirements":"= 1.10.0"}]}},"vcs_name":"GitHub","ci":1,"github_actions":1,"vcs_uri":"https://github.com/judoscale/judoscale-ruby"}