{"gems":{"name":"rails_admin","downloads":9678406,"version":"3.1.4","version_created_at":"2024-07-09T11:16:37.191Z","version_downloads":23,"platform":"ruby","authors":"Erik Michaels-Ober, Bogdan Gaza, Petteri Kaapa, Benoit Benezech, Mitsuhiro Shibuya","info":"RailsAdmin is a Rails engine that provides an easy-to-use interface for managing your data.","licenses":["MIT"],"metadata":{},"yanked":false,"sha":"d564277b6955aae900f8403e918678ad44b702a6f7efdc494750fc69fbb6911b","spec_sha":"9b9aca8208f09dc611c7ae419012237565bb023407cdf6e5cf5b10e6e49ab583","project_uri":"https://rubygems.org/gems/rails_admin","gem_uri":"https://rubygems.org/gems/rails_admin-3.1.4.gem","homepage_uri":"https://github.com/railsadminteam/rails_admin","wiki_uri":"https://github.com/sferik/rails_admin/wiki","documentation_uri":"https://www.rubydoc.info/gems/rails_admin/3.1.4","mailing_list_uri":"http://groups.google.com/group/rails_admin","source_code_uri":"https://github.com/sferik/rails_admin","bug_tracker_uri":"https://github.com/sferik/rails_admin/issues","changelog_uri":null,"funding_uri":null,"dependencies":{"development":[{"name":"bundler","requirements":">= 1.0"}],"runtime":[{"name":"activemodel-serializers-xml","requirements":">= 1.0"},{"name":"kaminari","requirements":">= 0.14, < 2.0"},{"name":"nested_form","requirements":"~> 0.3"},{"name":"rails","requirements":">= 6.0, < 8"},{"name":"turbo-rails","requirements":"~> 1.0"}]}},"vcs_name":"GitHub","ci":null,"vcs_error":"ERROR","vcs_uri":"https://github.com/sferik/rails_admin"}