{"gems":{"name":"loops_rails","downloads":52,"version":"0.1.1","version_created_at":"2024-07-10T10:05:48.571Z","version_downloads":18,"platform":"ruby","authors":"Daniel Friis","info":"Rails integration for Loops","licenses":["MIT"],"metadata":{"homepage_uri":"https://github.com/danielfriis/loops_rails","source_code_uri":"https://github.com/danielfriis/loops_rails","allowed_push_host":"https://rubygems.org"},"yanked":false,"sha":"228c162fe3b1cd854010ffed0ccf5f410bbee529b180d8d04f61ba10cfef45bc","spec_sha":"3ea8efa5dcbc62f0e13cdaf174b96fb81fea17f208a4c939741d39d8391ac279","project_uri":"https://rubygems.org/gems/loops_rails","gem_uri":"https://rubygems.org/gems/loops_rails-0.1.1.gem","homepage_uri":"https://github.com/danielfriis/loops_rails","wiki_uri":null,"documentation_uri":null,"mailing_list_uri":null,"source_code_uri":"https://github.com/danielfriis/loops_rails","bug_tracker_uri":null,"changelog_uri":null,"funding_uri":null,"dependencies":{"development":[],"runtime":[{"name":"faraday","requirements":">= 0"}]}},"vcs_name":"GitHub","ci":null,"vcs_uri":"https://github.com/danielfriis/loops_rails"}