{"gems":{"name":"jamm","downloads":2789,"version":"1.1.1","version_created_at":"2025-04-02T02:27:23.641Z","version_downloads":0,"platform":"ruby","authors":"Jamm","info":"Jamm help you make payment without credit cards","licenses":["MIT"],"metadata":{"source_code_uri":"https://github.com/jamm-pay/Jamm-SDK-Ruby"},"yanked":false,"sha":"1cba790caaa1f6513bba37437204e92355a28706ae141c56b1e62685b225f328","spec_sha":"2118953bf4ab5d20a7c2c631aa019d676e00e750f6b3a79e5dba2c9a13092c9d","project_uri":"https://rubygems.org/gems/jamm","gem_uri":"https://rubygems.org/gems/jamm-1.1.1.gem","homepage_uri":null,"wiki_uri":null,"documentation_uri":null,"mailing_list_uri":null,"source_code_uri":"https://github.com/jamm-pay/Jamm-SDK-Ruby","bug_tracker_uri":null,"changelog_uri":null,"funding_uri":null,"dependencies":{"development":[],"runtime":[{"name":"rest-client","requirements":"~> 2.0"},{"name":"typhoeus","requirements":"~> 1.0, >= 1.0.1"}]}},"vcs_name":"GitHub","ci":null,"vcs_error":"ERROR","vcs_uri":"https://github.com/jamm-pay/Jamm-SDK-Ruby"}