{"gems":{"name":"shiprocket_api","downloads":14826,"version":"0.8.0","version_created_at":"2022-11-01T07:43:43.855Z","version_downloads":0,"platform":"ruby","authors":"Andy Chong","info":"Ruby object based Sendle API wrapper.","licenses":["MIT"],"metadata":{"homepage_uri":"https://github.com/PostCo/sendle_api","changelog_uri":"https://github.com/PostCo/shiprocket_api/releases","source_code_uri":"https://github.com/PostCo/shiprocket_api","allowed_push_host":"https://rubygems.org/"},"yanked":false,"sha":"1d028729861a0d74228bbce145e9515041296b82b62301a4145f1ab9b6673b5c","project_uri":"https://rubygems.org/gems/shiprocket_api","gem_uri":"https://rubygems.org/gems/shiprocket_api-0.8.0.gem","homepage_uri":"https://github.com/PostCo/sendle_api","wiki_uri":null,"documentation_uri":null,"mailing_list_uri":null,"source_code_uri":"https://github.com/PostCo/shiprocket_api","bug_tracker_uri":null,"changelog_uri":"https://github.com/PostCo/shiprocket_api/releases","funding_uri":null,"dependencies":{"development":[{"name":"dotenv","requirements":">= 0"},{"name":"guard-rspec","requirements":">= 0"},{"name":"pry","requirements":">= 0"},{"name":"pry-byebug","requirements":">= 0"},{"name":"rspec","requirements":"~> 3.2"},{"name":"zeitwerk","requirements":">= 0"}],"runtime":[{"name":"activeresource","requirements":">= 4.1.0"},{"name":"http","requirements":">= 0"}]}},"vcs_name":"GitHub","ci":1,"travis_ci":1,"vcs_uri":"https://github.com/PostCo/shiprocket_api"}