{"gems":{"name":"eyes_selenium","downloads":1508572,"version":"6.0.4","version_created_at":"2024-02-05T14:46:04.051Z","version_downloads":5,"platform":"ruby","authors":"Applitools Team","info":"Provides SDK for writing Applitools Selenium-based tests","licenses":["Applitools"],"metadata":{},"yanked":false,"sha":"6cc2a60d4e0e82eeaf64079ac56d388e39f68315f1895a78c8ea125f3095c5f4","project_uri":"https://rubygems.org/gems/eyes_selenium","gem_uri":"https://rubygems.org/gems/eyes_selenium-6.0.4.gem","homepage_uri":"https://www.applitools.com","wiki_uri":"https://applitools.com/resources/tutorial/selenium/ruby#step-2","documentation_uri":"https://www.rubydoc.info/gems/eyes_selenium/6.0.4","mailing_list_uri":"","source_code_uri":"https://github.com/applitools/eyes.sdk.ruby","bug_tracker_uri":"","changelog_uri":null,"funding_uri":null,"dependencies":{"development":[],"runtime":[{"name":"crass","requirements":">= 0"},{"name":"css_parser","requirements":">= 0"},{"name":"eyes_core","requirements":"= 6.0.4"},{"name":"selenium-webdriver","requirements":">= 3"},{"name":"state_machines","requirements":">= 0"}]}},"vcs_name":"GitHub","ci":1,"travis_ci":1,"vcs_uri":"https://github.com/applitools/eyes.sdk.ruby"}