{"gems":{"name":"params-registry","downloads":4130,"version":"0.2.2","version_created_at":"2025-03-27T23:32:53.250Z","version_downloads":41,"platform":"ruby","authors":"Dorian Taylor","info":"# `Params::Registry`: A registry for named parameters\n\n\n","licenses":["Apache-2.0"],"metadata":{"homepage_uri":"https://github.com/doriantaylor/rb-params-registry","source_code_uri":"https://github.com/doriantaylor/rb-params-registry"},"yanked":false,"sha":"a32d076219225ca8269c50e491ad782679a02f5af553985945e40ef2bd3db53d","spec_sha":"9a58c7a98b0d199cc44803d5db6e4e2e105335e8c5faec1cfa6ce291f87c648a","project_uri":"https://rubygems.org/gems/params-registry","gem_uri":"https://rubygems.org/gems/params-registry-0.2.2.gem","homepage_uri":"https://github.com/doriantaylor/rb-params-registry","wiki_uri":null,"documentation_uri":null,"mailing_list_uri":null,"source_code_uri":"https://github.com/doriantaylor/rb-params-registry","bug_tracker_uri":null,"changelog_uri":null,"funding_uri":null,"dependencies":{"development":[],"runtime":[{"name":"dry-types","requirements":"~> 1.7"}]}},"vcs_name":"GitHub","ci":null,"vcs_uri":"https://github.com/doriantaylor/rb-params-registry"}