{"gems":{"name":"pay","downloads":1518261,"version":"11.4.3","version_created_at":"2025-12-23T18:45:10.145Z","version_downloads":9,"platform":"ruby","authors":"Jason Charnes, Chris Oliver, Collin Jilbert","info":"Stripe, Paddle, and Braintree payments for Ruby on Rails apps","licenses":["MIT"],"metadata":{},"yanked":false,"sha":"f3d50b1a900ab0a7bfe9ba9fda631b2f5faf0c95236dd3d2afa9effc9bfb15e8","spec_sha":"5071cd7896b7c26ba287d1db77e3139a8b8e3da2d1c5596fef077bbeb792665d","project_uri":"https://rubygems.org/gems/pay","gem_uri":"https://rubygems.org/gems/pay-11.4.3.gem","homepage_uri":"https://github.com/pay-rails/pay","wiki_uri":null,"documentation_uri":"https://www.rubydoc.info/gems/pay/11.4.3","mailing_list_uri":null,"source_code_uri":null,"bug_tracker_uri":null,"changelog_uri":null,"funding_uri":null,"dependencies":{"development":[],"runtime":[{"name":"rails","requirements":">= 7.0.0"}]}},"vcs_name":"GitHub","ci":1,"github_actions":1,"vcs_uri":"https://github.com/pay-rails/pay"}