{"gems":{"name":"hiiro","downloads":5483,"version":"0.1.58","version_created_at":"2026-02-08T23:05:06.185Z","version_downloads":0,"platform":"ruby","authors":"Joshua Toyota","info":"Build multi-command CLI tools with subcommand dispatch, abbreviation matching, and a plugin system. Similar to git or docker command structure.","licenses":["MIT"],"metadata":{"homepage_uri":"https://github.com/unixsuperhero/hiiro","changelog_uri":"https://github.com/unixsuperhero/hiiro/blob/main/CHANGELOG.md","source_code_uri":"https://github.com/unixsuperhero/hiiro"},"yanked":false,"sha":"719aebd90239c8bddcfb2db01f77eda686aa2178a70b314c390a638a6fa8048f","spec_sha":"f4e00455b5b038a7f852aa278e99f22ab3583ee3b6b0a1af1ed8453e5f842b1d","project_uri":"https://rubygems.org/gems/hiiro","gem_uri":"https://rubygems.org/gems/hiiro-0.1.58.gem","homepage_uri":"https://github.com/unixsuperhero/hiiro","wiki_uri":null,"documentation_uri":null,"mailing_list_uri":null,"source_code_uri":"https://github.com/unixsuperhero/hiiro","bug_tracker_uri":null,"changelog_uri":"https://github.com/unixsuperhero/hiiro/blob/main/CHANGELOG.md","funding_uri":null,"dependencies":{"development":[{"name":"minitest","requirements":"~> 5.0"},{"name":"rake","requirements":"~> 13.0"}],"runtime":[{"name":"pry","requirements":"~> 0.14"}]}},"vcs_name":"GitHub","ci":null,"vcs_uri":"https://github.com/unixsuperhero/hiiro"}