{"gems":{"name":"config_default","downloads":19624,"version":"0.6.3","version_created_at":"2026-05-05T17:01:01.318Z","version_downloads":22,"platform":"ruby","authors":"Stepan Kirushkin","info":"    ConfigDefault add an ability to separate your configuration on *.default.yml and *.yml files.\n    It's very useful to mix in configuration when you deploy your application.\n","licenses":["MIT"],"metadata":{"homepage_uri":"https://github.com/skirushkin/config_default","changelog_uri":"https://github.com/skirushkin/config_default/blob/master/CHANGELOG.md","source_code_uri":"https://github.com/skirushkin/config_default"},"yanked":false,"sha":"7a380a003c1d553cd6da52e41beadba3d985a0c78cbae776381af038c2cb87db","spec_sha":"8e69e2b7e79ec0dff86753004748da45b2914ae36dfe00ff2ac464ad9f648808","project_uri":"https://rubygems.org/gems/config_default","gem_uri":"https://rubygems.org/gems/config_default-0.6.3.gem","homepage_uri":"https://github.com/skirushkin/config_default","wiki_uri":null,"documentation_uri":null,"mailing_list_uri":null,"source_code_uri":"https://github.com/skirushkin/config_default","bug_tracker_uri":null,"changelog_uri":"https://github.com/skirushkin/config_default/blob/master/CHANGELOG.md","funding_uri":null,"dependencies":{"development":[],"runtime":[{"name":"activesupport","requirements":">= 6"}]}},"vcs_name":"GitHub","ci":1,"github_actions":1,"vcs_uri":"https://github.com/skirushkin/config_default"}