{"gems":{"name":"aws-sdk-ssmsap","downloads":8077647,"version":"1.25.0","version_created_at":"2024-09-03T20:16:22.575Z","version_downloads":1176,"platform":"ruby","authors":"Amazon Web Services","info":"Official AWS Ruby gem for AWS Systems Manager for SAP (SsmSap). This gem is part of the AWS SDK for Ruby.","licenses":["Apache-2.0"],"metadata":{"changelog_uri":"https://github.com/aws/aws-sdk-ruby/tree/version-3/gems/aws-sdk-ssmsap/CHANGELOG.md","source_code_uri":"https://github.com/aws/aws-sdk-ruby/tree/version-3/gems/aws-sdk-ssmsap"},"yanked":false,"sha":"2e0fd3610c3cd1ee37d93ec2eac0ffd3f3de9d40df6d3c4a791b0cb0248965d9","spec_sha":"bb0127fc723698ff3101dd388284006edc7263184dc731954761ded5d6a3c6f9","project_uri":"https://rubygems.org/gems/aws-sdk-ssmsap","gem_uri":"https://rubygems.org/gems/aws-sdk-ssmsap-1.25.0.gem","homepage_uri":"https://github.com/aws/aws-sdk-ruby","wiki_uri":null,"documentation_uri":null,"mailing_list_uri":null,"source_code_uri":"https://github.com/aws/aws-sdk-ruby/tree/version-3/gems/aws-sdk-ssmsap","bug_tracker_uri":null,"changelog_uri":"https://github.com/aws/aws-sdk-ruby/tree/version-3/gems/aws-sdk-ssmsap/CHANGELOG.md","funding_uri":null,"dependencies":{"development":[],"runtime":[{"name":"aws-sdk-core","requirements":"~> 3, >= 3.203.0"},{"name":"aws-sigv4","requirements":"~> 1.5"}]}},"vcs_name":"GitHub","ci":null,"vcs_error":"ERROR","vcs_uri":"https://github.com/aws/aws-sdk-ruby/tree/version-3/gems/aws-sdk-ssmsap"}