{"gems":{"name":"aws-sdk-iam","downloads":131789612,"version":"1.131.0","version_created_at":"2025-10-22T20:24:24.690Z","version_downloads":77,"platform":"ruby","authors":"Amazon Web Services","info":"Official AWS Ruby gem for AWS Identity and Access Management (IAM). This gem is part of the AWS SDK for Ruby.","licenses":["Apache-2.0"],"metadata":{"changelog_uri":"https://github.com/aws/aws-sdk-ruby/tree/version-3/gems/aws-sdk-iam/CHANGELOG.md","source_code_uri":"https://github.com/aws/aws-sdk-ruby/tree/version-3/gems/aws-sdk-iam"},"yanked":false,"sha":"b92767602c98b4ae56e05661d0e2172a0e8c30a6df1daefe82d006ca79bbc00d","spec_sha":"7fcf75e44fa6416d136bf78f34d7db93e7fdc176b2b4139f66647086b67b6e0b","project_uri":"https://rubygems.org/gems/aws-sdk-iam","gem_uri":"https://rubygems.org/gems/aws-sdk-iam-1.131.0.gem","homepage_uri":"https://github.com/aws/aws-sdk-ruby","wiki_uri":null,"documentation_uri":null,"mailing_list_uri":null,"source_code_uri":"https://github.com/aws/aws-sdk-ruby/tree/version-3/gems/aws-sdk-iam","bug_tracker_uri":null,"changelog_uri":"https://github.com/aws/aws-sdk-ruby/tree/version-3/gems/aws-sdk-iam/CHANGELOG.md","funding_uri":null,"dependencies":{"development":[],"runtime":[{"name":"aws-sdk-core","requirements":"~> 3, >= 3.234.0"},{"name":"aws-sigv4","requirements":"~> 1.5"}]}},"vcs_name":"GitHub","ci":null,"vcs_error":"ERROR","vcs_uri":"https://github.com/aws/aws-sdk-ruby/tree/version-3/gems/aws-sdk-iam"}