{"gems":{"name":"active_capture","downloads":224,"version":"1.1.0","version_created_at":"2025-03-31T14:31:27.102Z","version_downloads":14,"platform":"ruby","authors":"Tanmay Bhawsar","info":"ActiveCapture allows you to save captures of ActiveRecord records, including their nested associations, and restore them at any point. Useful for auditing, backups, and rollback functionality.","licenses":["MIT"],"metadata":{"homepage_uri":"https://github.com/bhawsartanmay/active_capture","source_code_uri":"https://github.com/bhawsartanmay/active_capture"},"yanked":false,"sha":"9d42507cd4c76c43ac863853a57a19d6d2b1d0402b47239ab2e836f0c1661090","spec_sha":"f723b82b4bc5678190f0c281dd4c51d3f9abdaa5ece3907213e1e1ff34251e29","project_uri":"https://rubygems.org/gems/active_capture","gem_uri":"https://rubygems.org/gems/active_capture-1.1.0.gem","homepage_uri":"https://github.com/bhawsartanmay/active_capture","wiki_uri":null,"documentation_uri":null,"mailing_list_uri":null,"source_code_uri":"https://github.com/bhawsartanmay/active_capture","bug_tracker_uri":null,"changelog_uri":null,"funding_uri":null,"dependencies":{"development":[{"name":"minitest","requirements":"~> 5.0"}],"runtime":[]}},"vcs_name":"GitHub","ci":null,"vcs_error":"ERROR","vcs_uri":"https://github.com/bhawsartanmay/active_capture"}