{"gems":{"name":"wolf_core","downloads":2507,"version":"0.1.23","version_created_at":"2024-07-17T21:24:34.139Z","version_downloads":42,"platform":"ruby","authors":"Javier Roncallo","info":"Repository to store shared code among Ruby projects.","licenses":[],"metadata":{"homepage_uri":"https://github.com/onewolfxyz/wolf_core","changelog_uri":"https://github.com/onewolfxyz/wolf_core","source_code_uri":"https://github.com/onewolfxyz/wolf_core","allowed_push_host":"https://rubygems.org"},"yanked":false,"sha":"8062e40690bb20c912036ec068d633ce0ebf3a6870b8f6038af9f92d0951b046","spec_sha":"1d878f1a020cd94ab0dbb519fcba31857e3ed5f4eb72258e57444a30062f942b","project_uri":"https://rubygems.org/gems/wolf_core","gem_uri":"https://rubygems.org/gems/wolf_core-0.1.23.gem","homepage_uri":"https://github.com/onewolfxyz/wolf_core","wiki_uri":null,"documentation_uri":null,"mailing_list_uri":null,"source_code_uri":"https://github.com/onewolfxyz/wolf_core","bug_tracker_uri":null,"changelog_uri":"https://github.com/onewolfxyz/wolf_core","funding_uri":null,"dependencies":{"development":[],"runtime":[{"name":"activesupport","requirements":">= 0"},{"name":"aws-sdk-lambda","requirements":">= 0"},{"name":"httparty","requirements":">= 0"}]}},"vcs_name":"GitHub","ci":null,"vcs_error":"ERROR","vcs_uri":"https://github.com/onewolfxyz/wolf_core"}