{"gems":{"name":"wowsql-sdk","downloads":2073,"version":"3.0.1","version_created_at":"2026-03-19T21:21:10.964Z","version_downloads":34,"platform":"ruby","authors":"WOWSQL Team","info":"Official Ruby client library for WOWSQL - PostgreSQL Backend-as-a-Service with Object Storage","licenses":["MIT"],"metadata":{},"yanked":false,"sha":"c1b7886fa18e319120b0e1d2ceb75df8bc11feb060a503c1fb489418033c5205","spec_sha":"46aff2003fa6ea120aceac48dd9ff166e05facbfe698611cf8a0ceb85a7787cb","project_uri":"https://rubygems.org/gems/wowsql-sdk","gem_uri":"https://rubygems.org/gems/wowsql-sdk-3.0.1.gem","homepage_uri":"https://github.com/wowsql/wowsql-sdk-ruby","wiki_uri":null,"documentation_uri":"https://www.rubydoc.info/gems/wowsql-sdk/3.0.1","mailing_list_uri":null,"source_code_uri":null,"bug_tracker_uri":null,"changelog_uri":null,"funding_uri":null,"dependencies":{"development":[{"name":"rake","requirements":"~> 13.0"},{"name":"rspec","requirements":"~> 3.0"}],"runtime":[{"name":"faraday","requirements":"~> 2.0"},{"name":"faraday-multipart","requirements":"~> 1.0"},{"name":"json","requirements":"~> 2.0"}]}},"vcs_name":"GitHub","ci":null,"vcs_error":"ERROR","vcs_uri":"https://github.com/wowsql/wowsql-sdk-ruby"}