{"gems":{"name":"view_component-form","downloads":266383,"version":"0.2.10","version_created_at":"2025-03-17T16:07:31.321Z","version_downloads":30,"platform":"ruby","authors":"Pantographe","info":"Rails FormBuilder for ViewComponent","licenses":["MIT"],"metadata":{"homepage_uri":"https://github.com/pantographe/view_component-form","changelog_uri":"https://github.com/pantographe/view_component-form/blob/master/CHANGELOG.md","bug_tracker_uri":"https://github.com/pantographe/view_component-form/issues","source_code_uri":"https://github.com/pantographe/view_component-form","rubygems_mfa_required":"true"},"yanked":false,"sha":"a4304bf0a57c93693eb61f11873170ca7bfb2409f998c439f7a9fa010864a9cc","spec_sha":"276a6238367e80d56771a86e19c8ddbe32c54344f31d26118278cecb133ea021","project_uri":"https://rubygems.org/gems/view_component-form","gem_uri":"https://rubygems.org/gems/view_component-form-0.2.10.gem","homepage_uri":"https://github.com/pantographe/view_component-form","wiki_uri":null,"documentation_uri":null,"mailing_list_uri":null,"source_code_uri":"https://github.com/pantographe/view_component-form","bug_tracker_uri":"https://github.com/pantographe/view_component-form/issues","changelog_uri":"https://github.com/pantographe/view_component-form/blob/master/CHANGELOG.md","funding_uri":null,"dependencies":{"development":[],"runtime":[{"name":"actionview","requirements":">= 7.0.0, < 8.1"},{"name":"activesupport","requirements":">= 7.0.0, < 8.1"},{"name":"view_component","requirements":">= 2.34.0, < 4.0"},{"name":"zeitwerk","requirements":"~> 2.5"}]}},"vcs_name":"GitHub","ci":1,"github_actions":1,"vcs_uri":"https://github.com/pantographe/view_component-form"}