{"gems":{"name":"jekyll-obsidian","downloads":1098,"version":"1.1.5","version_created_at":"2025-01-09T09:35:46.026Z","version_downloads":13,"platform":"ruby","authors":"Khiem Luong","info":"Jekyll site implementation of obsidian as close to how it looks in the app","licenses":["MIT"],"metadata":{"homepage_uri":"https://khiemgluong.github.io/blade-ballad/","changelog_uri":"https://github.com/khiemgluong/jekyll-obsidian/blob/main/CHANGELOG.md","source_code_uri":"https://github.com/khiemgluong/jekyll-obsidian/"},"yanked":false,"sha":"3c89bfbade228ccdcdad2482b5a9cb28496a6f38723d6a9ae2b8c7bbd9fd83dd","spec_sha":"2a5b449c898d977c07c7ce1a948139f5cc0485eac3f16531a58d7a8420c215e3","project_uri":"https://rubygems.org/gems/jekyll-obsidian","gem_uri":"https://rubygems.org/gems/jekyll-obsidian-1.1.5.gem","homepage_uri":"https://khiemgluong.github.io/blade-ballad/","wiki_uri":null,"documentation_uri":null,"mailing_list_uri":null,"source_code_uri":"https://github.com/khiemgluong/jekyll-obsidian/","bug_tracker_uri":null,"changelog_uri":"https://github.com/khiemgluong/jekyll-obsidian/blob/main/CHANGELOG.md","funding_uri":null,"dependencies":{"development":[{"name":"rspec","requirements":"~> 3.0"}],"runtime":[{"name":"jekyll","requirements":"~> 4.0"}]}},"vcs_name":"GitHub","ci":1,"github_actions":1,"vcs_uri":"https://github.com/khiemgluong/jekyll-obsidian/"}