{"gems":{"name":"bulma-clean-theme","downloads":103065,"version":"1.1.0","version_created_at":"2024-09-01T19:07:52.742Z","version_downloads":30,"platform":"ruby","authors":"chrisrhymes","info":"Clean and simple Jekyll theme built using Bulma","licenses":["MIT"],"metadata":{},"yanked":false,"sha":"e333f3672f8d161bc2a8284c5d4933b1ac5dba25e8bfb25b6f22ad9af8f45596","spec_sha":"052a457b9ab7bfe00c15f853c64cef199ac993dbfb657417dc03b5b4243fccfd","project_uri":"https://rubygems.org/gems/bulma-clean-theme","gem_uri":"https://rubygems.org/gems/bulma-clean-theme-1.1.0.gem","homepage_uri":"https://www.github.com/chrisrhymes/bulma-clean-theme","wiki_uri":"","documentation_uri":"https://github.com/chrisrhymes/bulma-clean-theme/blob/master/README.md","mailing_list_uri":"","source_code_uri":"https://github.com/chrisrhymes/bulma-clean-theme","bug_tracker_uri":"https://github.com/chrisrhymes/bulma-clean-theme/issues","changelog_uri":null,"funding_uri":null,"dependencies":{"development":[{"name":"bundler","requirements":"~> 2.0"},{"name":"rake","requirements":"~> 12.0"}],"runtime":[{"name":"jekyll","requirements":">= 4.3, < 5.0"},{"name":"jekyll-feed","requirements":"~> 0.15"},{"name":"jekyll-paginate","requirements":"~> 1.1"},{"name":"jekyll-seo-tag","requirements":"~> 2.7"},{"name":"jekyll-sitemap","requirements":"~> 1.4"},{"name":"kramdown-parser-gfm","requirements":"~> 1.1"}]}},"vcs_name":"GitHub","ci":1,"github_actions":1,"vcs_uri":"https://github.com/chrisrhymes/bulma-clean-theme"}