{"gems":{"name":"pick_me_too","downloads":732,"version":"1.1.2","version_created_at":"2022-11-06T13:07:38.103Z","version_downloads":3,"platform":"ruby","authors":"David F. Houghton","info":"PickMeToo is a Ruby urn model. It allows you to generate an \"urn\" from which you can randomly sample items with specified frequencies. This facilitates modeling things that occur with known frequencies, like weather or wandering monsters.","licenses":["MIT"],"metadata":{},"yanked":false,"sha":"8829c66898f87d5d760bc2d7791fa9e165997e944a27d33438895b2ebeb905b4","project_uri":"https://rubygems.org/gems/pick_me_too","gem_uri":"https://rubygems.org/gems/pick_me_too-1.1.2.gem","homepage_uri":"https://github.com/dfhoughton/pick_me_too","wiki_uri":null,"documentation_uri":"https://www.rubydoc.info/gems/pick_me_too/1.1.2","mailing_list_uri":null,"source_code_uri":null,"bug_tracker_uri":null,"changelog_uri":null,"funding_uri":null,"dependencies":{"development":[{"name":"bundler","requirements":"~> 1.7"},{"name":"byebug","requirements":"~> 9.1, >= 9.1.0"},{"name":"json","requirements":"~> 2"},{"name":"minitest","requirements":"~> 5"},{"name":"rake","requirements":"~> 10.0"}],"runtime":[]}},"vcs_name":"GitHub","ci":null,"vcs_uri":"https://github.com/dfhoughton/pick_me_too"}