{"gems":{"name":"strapi_ruby","downloads":68,"version":"0.1.2","version_created_at":"2023-10-11T12:18:31.009Z","version_downloads":20,"platform":"ruby","authors":"Maxence Robinet","info":"  StrapiRuby is a Ruby gem designed to simplify interactions\n  with the Strapi CMS API. It provides an easy-to-use interface for\n  making requests to a Strapi server and handling responses.\n","licenses":["MIT"],"metadata":{"homepage_uri":"https://github.com/saint-james-fr/strapi_ruby","changelog_uri":"https://github.com/saint-james-fr/strapi_ruby/blob/master/CHANGELOG.md","source_code_uri":"https://github.com/saint-james-fr/strapi_ruby"},"yanked":false,"sha":"ac0c3256bcdef99829d0b2dee0ed7104332a0aaaf11a97b1d5c97b1189ef8444","project_uri":"https://rubygems.org/gems/strapi_ruby","gem_uri":"https://rubygems.org/gems/strapi_ruby-0.1.2.gem","homepage_uri":"https://github.com/saint-james-fr/strapi_ruby","wiki_uri":null,"documentation_uri":null,"mailing_list_uri":null,"source_code_uri":"https://github.com/saint-james-fr/strapi_ruby","bug_tracker_uri":null,"changelog_uri":"https://github.com/saint-james-fr/strapi_ruby/blob/master/CHANGELOG.md","funding_uri":null,"dependencies":{"development":[{"name":"dotenv","requirements":"~> 2.8"},{"name":"webmock","requirements":"~> 3.19"}],"runtime":[{"name":"colorize","requirements":"~> 1.1.0"},{"name":"faraday","requirements":"~> 2.7"},{"name":"redcarpet","requirements":"~> 3.6"}]}},"vcs_name":"GitHub","ci":1,"github_actions":1,"vcs_uri":"https://github.com/saint-james-fr/strapi_ruby"}