{"gems":{"name":"zon-rb","downloads":74,"version":"0.2.0","version_created_at":"2025-09-27T19:25:46.815Z","version_downloads":23,"platform":"ruby","authors":"David P. Sugar","info":"This gem allows you to translate Zig Object Notation (ZON) data into Ruby objects and vice versa.","licenses":["MIT"],"metadata":{"homepage_uri":"https://github.com/r4gus/zon-rb","changelog_uri":"https://github.com/r4gus/zon-rb/blob/master/CHANGELOG.md","source_code_uri":"https://github.com/r4gus/zon-rb"},"yanked":false,"sha":"668e3786986f6d915234232067a36dc5b46c6d088a9c4aef7c9afac2a102feca","spec_sha":"6fcaef14f49ccc97e756ca280bc3bd3fd8830d76b3e16fad0c83f900d8b94847","project_uri":"https://rubygems.org/gems/zon-rb","gem_uri":"https://rubygems.org/gems/zon-rb-0.2.0.gem","homepage_uri":"https://github.com/r4gus/zon-rb","wiki_uri":null,"documentation_uri":null,"mailing_list_uri":null,"source_code_uri":"https://github.com/r4gus/zon-rb","bug_tracker_uri":null,"changelog_uri":"https://github.com/r4gus/zon-rb/blob/master/CHANGELOG.md","funding_uri":null,"dependencies":{"development":[],"runtime":[]}},"vcs_name":"GitHub","ci":null,"vcs_uri":"https://github.com/r4gus/zon-rb"}