{"gems":{"name":"capim_tictactoe","downloads":820,"version":"1.0.0","version_created_at":"2023-01-11T20:38:23.697Z","version_downloads":0,"platform":"ruby","authors":"Gustavo Maia","info":"This gem is a coding challenge proposed by @capim","licenses":["MIT"],"metadata":{"github_repo":"ssh://github.com/itsmaia/capimtictactoe-gem"},"yanked":false,"sha":"d49850b6d8152d0c5a2d7bc8f4e2481397361fa27c3e4154ca879c2ab8b8d6ad","project_uri":"https://rubygems.org/gems/capim_tictactoe","gem_uri":"https://rubygems.org/gems/capim_tictactoe-1.0.0.gem","homepage_uri":"https://github.com/itsmaia/blank","wiki_uri":null,"documentation_uri":"https://www.rubydoc.info/gems/capim_tictactoe/1.0.0","mailing_list_uri":null,"source_code_uri":null,"bug_tracker_uri":null,"changelog_uri":null,"funding_uri":null,"dependencies":{"development":[{"name":"rspec","requirements":">= 0"},{"name":"rubocop","requirements":">= 0"}],"runtime":[{"name":"rainbow","requirements":">= 0"}]}},"vcs_name":"GitHub","ci":null,"vcs_error":"ERROR","vcs_uri":"https://github.com/itsmaia/blank"}