{"gems":{"name":"komoju-sdk","downloads":335,"version":"1.0.0","version_created_at":"2026-06-29T06:56:53.777Z","version_downloads":112,"platform":"ruby","authors":"KOMOJU Co., Ltd.","info":"Full featured access to the KOMOJU payments system.","licenses":["MIT"],"metadata":{},"yanked":false,"sha":"a068fc6167234b8c76500e01bc7c62ee8848ecf11855f74474c4ab9e52544299","spec_sha":"bc9fe7c0dc460ac1bd7f5bdd33ee591ea52183776d8e9e977d704a9f14825b1c","project_uri":"https://rubygems.org/gems/komoju-sdk","gem_uri":"https://rubygems.org/gems/komoju-sdk-1.0.0.gem","homepage_uri":"https://github.com/komoju/komoju-ruby-sdk","wiki_uri":null,"documentation_uri":"https://www.rubydoc.info/gems/komoju-sdk/1.0.0","mailing_list_uri":null,"source_code_uri":null,"bug_tracker_uri":null,"changelog_uri":null,"funding_uri":null,"dependencies":{"development":[{"name":"rspec","requirements":"~> 3.6, >= 3.6.0"}],"runtime":[{"name":"faraday","requirements":">= 2.14.2, < 3.0"},{"name":"faraday-multipart","requirements":"~> 1.0"},{"name":"marcel","requirements":"~> 1.0"}]}},"vcs_name":"GitHub","ci":1,"github_actions":1,"vcs_uri":"https://github.com/komoju/komoju-ruby-sdk"}