{"gems":{"name":"beeps","downloads":29448,"version":"0.1.43","version_created_at":"2023-11-08T15:56:14.961Z","version_downloads":0,"platform":"ruby","authors":"xordog","info":"Synthesize and play beep sounds.","licenses":["MIT"],"metadata":{},"yanked":false,"sha":"07b4e5f82eab69f12ed1219fd324d10754849d4aa12bc4698b717ff9c9c11863","project_uri":"https://rubygems.org/gems/beeps","gem_uri":"https://rubygems.org/gems/beeps-0.1.43.gem","homepage_uri":"https://github.com/xord/beeps","wiki_uri":null,"documentation_uri":"https://www.rubydoc.info/gems/beeps/0.1.43","mailing_list_uri":null,"source_code_uri":null,"bug_tracker_uri":null,"changelog_uri":null,"funding_uri":null,"dependencies":{"development":[],"runtime":[{"name":"rucy","requirements":"~> 0.1.41"},{"name":"xot","requirements":"~> 0.1.40"}]}},"vcs_name":"GitHub","ci":1,"github_actions":1,"vcs_uri":"https://github.com/xord/beeps"}