{"gems":{"name":"birdspotting","downloads":49464,"version":"0.1.8","version_created_at":"2024-04-02T13:48:40.260Z","version_downloads":0,"platform":"ruby","authors":"Drivy, Howard Wilson, David Bourguignon, Alice Morin, Laurent Humez, Rémy Hannequin, Hugo Dornbierer","info":"Rails migration helpers.","licenses":["MIT"],"metadata":{},"yanked":false,"sha":"70520601f6812f4ec5109a64197ae1ba534299e90cb3050e4b10deb58dba05c3","project_uri":"https://rubygems.org/gems/birdspotting","gem_uri":"https://rubygems.org/gems/birdspotting-0.1.8.gem","homepage_uri":"https://github.com/drivy/birdspotting","wiki_uri":null,"documentation_uri":"https://www.rubydoc.info/gems/birdspotting/0.1.8","mailing_list_uri":null,"source_code_uri":null,"bug_tracker_uri":null,"changelog_uri":null,"funding_uri":null,"dependencies":{"development":[{"name":"bundler","requirements":">= 0"},{"name":"guard-rspec","requirements":">= 0"},{"name":"guard-rubocop","requirements":">= 0"},{"name":"rake","requirements":">= 0"},{"name":"rspec","requirements":">= 0"},{"name":"rspec_junit_formatter","requirements":">= 0"},{"name":"rubocop","requirements":">= 0"},{"name":"rubocop-rspec","requirements":">= 0"},{"name":"simplecov","requirements":">= 0"}],"runtime":[{"name":"activerecord","requirements":">= 6.1, < 7.1"}]}},"vcs_name":"GitHub","ci":1,"circleci":1,"vcs_uri":"https://github.com/drivy/birdspotting"}