{"gems":{"name":"fibered_mysql2","downloads":4084948,"version":"1.0.0","version_created_at":"2023-05-31T18:45:29.370Z","version_downloads":11,"platform":"ruby","authors":"Invoca Development","info":"An adapter for fibered mysql2","licenses":[],"metadata":{"homepage_uri":"https://github.com/Invoca/fibered_mysql2","allowed_push_host":"https://rubygems.org"},"yanked":false,"sha":"b140c9e8475c8b46daad6763027f66998dff007d3cc02c76674929c36243772e","project_uri":"https://rubygems.org/gems/fibered_mysql2","gem_uri":"https://rubygems.org/gems/fibered_mysql2-1.0.0.gem","homepage_uri":"https://github.com/Invoca/fibered_mysql2","wiki_uri":null,"documentation_uri":null,"mailing_list_uri":null,"source_code_uri":null,"bug_tracker_uri":null,"changelog_uri":null,"funding_uri":null,"dependencies":{"development":[],"runtime":[{"name":"async","requirements":">= 0"},{"name":"rails","requirements":">= 6, < 7"}]}},"vcs_name":"GitHub","ci":1,"github_actions":1,"vcs_uri":"https://github.com/Invoca/fibered_mysql2"}