{"gems":{"name":"bard-rake","downloads":227894,"version":"0.25.3","version_created_at":"2025-12-11T16:45:43.209Z","version_downloads":11,"platform":"ruby","authors":"Micah Geisel","info":"Rake tasks for all bard projects.\n* Bootstrap projects\n* Database backup","licenses":["MIT"],"metadata":{},"yanked":false,"sha":"28530f8038702bb458e809c936efa4b00ac34ada6f6156aff6c44ff64d4fa64c","spec_sha":"cc45b9149803ef317c90548ad118b8c21328984890fa482a00e2fe283d684e66","project_uri":"https://rubygems.org/gems/bard-rake","gem_uri":"https://rubygems.org/gems/bard-rake-0.25.3.gem","homepage_uri":"http://github.com/botandrose/bard-rake","wiki_uri":null,"documentation_uri":"https://www.rubydoc.info/gems/bard-rake/0.25.3","mailing_list_uri":null,"source_code_uri":null,"bug_tracker_uri":null,"changelog_uri":null,"funding_uri":null,"dependencies":{"development":[{"name":"bundler","requirements":">= 0"},{"name":"rspec","requirements":">= 1.2.9"}],"runtime":[{"name":"backhoe","requirements":">= 0.6.0"},{"name":"bard-backup","requirements":">= 0"},{"name":"railties","requirements":">= 0"},{"name":"rake","requirements":">= 0"}]}},"vcs_name":"GitHub","ci":null,"vcs_error":"ERROR","vcs_uri":"http://github.com/botandrose/bard-rake"}