{"gems":{"name":"omniauth-bokun","downloads":61,"version":"0.1.1","version_created_at":"2025-04-07T17:40:48.887Z","version_downloads":11,"platform":"ruby","authors":"Dmitry Sychev","info":"An unofficial OmniAuth strategy for Bokun, allowing authentication via Bokun's OAuth2 API.","licenses":["MIT"],"metadata":{"source_code_uri":"https://github.com/DmitrySychev/omniauth-bokun"},"yanked":false,"sha":"598e805a47cbc432ffc793449274b36a9f682da481c7363e9bb6a0d9df5d6cac","spec_sha":"40fb46be3caae4906871d110ec0b2d68318de909fceb86a00a3fe37e50f355b8","project_uri":"https://rubygems.org/gems/omniauth-bokun","gem_uri":"https://rubygems.org/gems/omniauth-bokun-0.1.1.gem","homepage_uri":null,"wiki_uri":null,"documentation_uri":null,"mailing_list_uri":null,"source_code_uri":"https://github.com/DmitrySychev/omniauth-bokun","bug_tracker_uri":null,"changelog_uri":null,"funding_uri":null,"dependencies":{"development":[{"name":"bundler","requirements":"~> 2.5"},{"name":"minitest","requirements":"~> 5.0"},{"name":"rake","requirements":"~> 10.0"}],"runtime":[{"name":"omniauth","requirements":"~> 2.0"},{"name":"omniauth-oauth2","requirements":"~> 1.8"}]}},"vcs_name":"GitHub","ci":1,"github_actions":1,"vcs_uri":"https://github.com/DmitrySychev/omniauth-bokun"}