{"gems":{"name":"isomorfeus-transport","downloads":102514,"version":"23.9.0.rc2","version_created_at":"2023-09-10T02:42:28.924Z","version_downloads":10,"platform":"ruby","authors":"Jan Biedermann","info":"Channels, authetication and various transport options for Isomorfeus.","licenses":["MIT"],"metadata":{"github_repo":"ssh://github.com/isomorfeus/gems","source_code_uri":"https://github.com/isomorfeus/isomorfeus-project/isomorfeus-transport"},"yanked":false,"sha":"f29cf32ab1a3f358dd3c91a9d194200503a88d5d65287d359194e243046f95cc","project_uri":"https://rubygems.org/gems/isomorfeus-transport","gem_uri":"https://rubygems.org/gems/isomorfeus-transport-23.9.0.rc2.gem","homepage_uri":"https://isomorfeus.com","wiki_uri":null,"documentation_uri":null,"mailing_list_uri":null,"source_code_uri":"https://github.com/isomorfeus/isomorfeus-project/isomorfeus-transport","bug_tracker_uri":null,"changelog_uri":null,"funding_uri":null,"dependencies":{"development":[{"name":"isomorfeus","requirements":"= 23.9.0.rc2"},{"name":"rake","requirements":">= 0"},{"name":"rspec","requirements":"~> 3.12.0"}],"runtime":[{"name":"activesupport","requirements":"~> 7.0.8"},{"name":"bcrypt","requirements":"~> 3.1.19"},{"name":"brotli","requirements":"~> 0.4.0"},{"name":"concurrent-ruby","requirements":"~> 1.2.2"},{"name":"isomorfeus-iodine","requirements":"~> 0.8.3"},{"name":"oj","requirements":">= 3.13.23, < 3.17.0"},{"name":"opal","requirements":"~> 1.8.0.alpha1"},{"name":"opal-zeitwerk","requirements":"~> 0.4.5"},{"name":"rack","requirements":"~> 3.0.8"},{"name":"rackup","requirements":"~> 2.1.0"},{"name":"zeitwerk","requirements":"~> 2.6.11"},{"name":"zlib","requirements":"~> 3.0.0"}]}},"vcs_name":"GitHub","ci":null,"vcs_error":"ERROR","vcs_uri":"https://github.com/isomorfeus/isomorfeus-project/isomorfeus-transport"}